comfy_models/__init__.py
comfy_models/cli.py
comfy_models/base/__init__.py
comfy_models/base/base_app.py
comfy_models/base/checkpoint_pickle.py
comfy_models/base/comfy_utils.py
comfy_models/base/docker.py
comfy_models/base/inputs.py
comfy_models/base/outputs.py
comfy_models/workflows/__init__.py
comfy_models/workflows/flux_dev/config.py
comfy_models/workflows/flux_dev/runner.py
comfy_models/workflows/flux_dev/workflow.json
comfy_models/workflows/flux_dev/workflow_api.json
comfy_models/workflows/flux_schnell/config.py
comfy_models/workflows/flux_schnell/runner.py
comfy_models/workflows/flux_schnell/workflow.json
comfy_models/workflows/flux_schnell/workflow_api.json
comfy_models/workflows/sd3_5_large/config.py
comfy_models/workflows/sd3_5_large/runner.py
comfy_models/workflows/sd3_5_large/workflow.json
comfy_models/workflows/sd3_5_large/workflow_api.json
comfy_models-0.1.5.dist-info/METADATA
comfy_models-0.1.5.dist-info/WHEEL
comfy_models-0.1.5.dist-info/entry_points.txt
comfy_models-0.1.5.dist-info/licenses/LICENSE
comfy_models-0.1.5.dist-info/RECORD
