Metadata-Version: 2.3
Name: comfy-models
Version: 0.1.5
Summary: Add your description here
License-File: LICENSE
Requires-Python: >=3.12
Requires-Dist: aiohttp>=3.10.10
Requires-Dist: click>=8.1.7
Requires-Dist: modal>=0.65.5
Requires-Dist: pydantic>=2.9.2
Requires-Dist: python-dotenv>=1.0.1
Requires-Dist: rich>=13.9.3
Requires-Dist: setuptools>=75.3.0
Requires-Dist: tabulate>=0.9.0
